mp_auth/__init__.py
mp_auth/models.py
mp_auth/backends/__init__.py
mp_auth/backends/base.py
mp_auth/backends/globus.py
mp_auth/backends/jwt.py
mp_auth/backends/mp.py
mp_auth/migrations/0001_initial.py
mp_auth/migrations/__init__.py
mp_auth-0.3.dist-info/LICENSE
mp_auth-0.3.dist-info/METADATA
mp_auth-0.3.dist-info/WHEEL
mp_auth-0.3.dist-info/top_level.txt
mp_auth-0.3.dist-info/RECORD
