Metadata-Version: 2.1
Name: mp-auth
Version: 0.3
Summary: Add Multi-provider auth for various providers
Home-page: UNKNOWN
Author: Globus Team
Author-email: support@globus.org
License: apache 2.0
Keywords: globus,django
Platform: UNKNOWN
Classifier: Intended Audience :: Developers
Classifier: License :: OSI Approved :: Apache Software License
Classifier: Operating System :: POSIX
Classifier: Programming Language :: Python
Classifier: Programming Language :: Python :: 3.4
Classifier: Programming Language :: Python :: 3.5
Classifier: Programming Language :: Python :: 3.6
Classifier: Programming Language :: Python :: 3.7
Classifier: Topic :: Communications :: File Sharing
Classifier: Topic :: Internet :: WWW/HTTP
Classifier: Topic :: Software Development :: Libraries :: Python Modules
Requires-Python: >=3.0
Requires-Dist: cryptography
Requires-Dist: PyJWT
Requires-Dist: requests
Requires-Dist: django
Requires-Dist: djangorestframework
